srds/__init__.py
srds/srds.py
tests/__init__.py
tests/test_srds.py
srds-0.1.0.dist-info/LICENSE
srds-0.1.0.dist-info/METADATA
srds-0.1.0.dist-info/WHEEL
srds-0.1.0.dist-info/top_level.txt
srds-0.1.0.dist-info/RECORD
