Metadata-Version: 2.1
Name: srds
Version: 0.1.0
Summary: Utilities for randomly sampling from statistical distributions
Home-page: https://github.com/thrau/srds
Author: Thomas Rausch
Author-email: thomas@rauschig.org
License: UNKNOWN
Download-URL: https://pypi.org/project/srds/
Platform: UNKNOWN
Classifier: Programming Language :: Python :: 3.6
Classifier: License :: OSI Approved :: MIT License
Classifier: Operating System :: OS Independent
Classifier: Development Status :: 4 - Beta
Requires-Dist: scipy (>=1.4.0)
